{"id": "1302.6810", "review": {"conference": "arxiv", "VERSION": "v1", "DATE_OF_SUBMISSION": "27-Feb-2013", "title": "Epsilon-Safe Planning", "abstract": "we likewise introduce importantly an experimental approach to modeling high - level conditional choice planning we call ] epsilon - gamma safe planning. \u2026 this probabilistic approach continuously commits us to planning to meet some specified specified goal with attaining a consistent probability of each success of supplying at least 1 - 3rd epsilon for some user - supplied epsilon. we describe formally several imperative algorithms for communicating epsilon - so safe planning based reasoning on varying conditional dependent planners. linking the two conditional planners we openly discuss critically are peot stokes and smith's nonlinear conditional catastrophe planner, ml cnlp, and our own linear conditional planner, plinth. while we present a single straightforward extension to conditional planners modeling for which only computing the not necessary estimated probabilities is simple, employing a similar commonly - made unexpected but equally perhaps overly - strong independence assumption. we also jointly discuss a quick second approach to epsilon - positive safe planning which dramatically relaxes fully this independence rule assumption, involving allowing the incremental internal construction of a probability dependence model ordered in full conjunction with the construction of preserving the plan zeta graph.", "histories": [["v1", "Wed, 27 Feb 2013 14:16:19 GMT  (1531kb)", "http://arxiv.org/abs/1302.6810v1", "Appears in Proceedings of the Tenth Conference on Uncertainty in Artificial Intelligence (UAI1994)"]], "COMMENTS": "Appears in Proceedings of the Tenth Conference on Uncertainty in Artificial Intelligence (UAI1994)", "reviews": [], "SUBJECTS": "cs.AI", "authors": ["robert p goldman", "mark s boddy"], "accepted": false, "id": "1302.6810"}, "pdf": {"name": "1302.6810.pdf", "metadata": {"source": "CRF", "title": null, "authors": ["MarkS. Boddy"], "emails": ["goldman@src.honeywell.com", "boddy@src.honeywell.com"], "sections": null, "references": [{"title": "Planning for image analysis", "author": ["Boddy et al", "1994] Boddy", "Mark S", "Robert P. Goldman", "J White"], "venue": "ames", "citeRegEx": ". et al\\.,? \\Q1994\\E", "shortCiteRegEx": ". et al\\.", "year": 1994}, {"title": "P robabilistic planning with information gathering and contingent execu\u00ad tion", "author": ["Draper et al", "1993] Draper", "Denise", "Steve Hanks", "Daniel Wel d"], "venue": "Technical Report", "citeRegEx": "Denise et al\\.,? \\Q1993\\E", "shortCiteRegEx": "Denise et al\\.", "year": 1993}, {"title": "Anytime synthetic projection : M aximizing the probabil ity of goal satis\u00ad", "author": ["Drummond", "Bresina", "1990] Drummond", "Mark", "John"], "venue": "Proceedings of the Eigh th National Con\u00ad ference on A rtificial Intelligence", "citeRegEx": "Drummond et al\\.,? \\Q1990\\E", "shortCiteRegEx": "Drummond et al\\.", "year": 1990}, {"title": "An approach to planning with incomplete information", "author": ["Etzioni"], "venue": null, "citeRegEx": "Etzioni,? \\Q1992\\E", "shortCiteRegEx": "Etzioni", "year": 1992}, {"title": "Conditional linear plan\u00ad n ing", "author": ["Goldman", "Boddy"], "venue": "A r\u00ad tificial Intelligence Plannzng Syst ems: Proceedings of the Second International Conference,", "citeRegEx": "Goldman and Boddy,? \\Q1994\\E", "shortCiteRegEx": "Goldman and Boddy", "year": 1994}, {"title": "Representing uncer\u00ad tainty i n simple p lanners", "author": ["Goldman", "Robert P", "Boddy", "M ark S"], "venue": "[Go ldman and Boddy,", "citeRegEx": "Goldman et al\\.,? \\Q1994\\E", "shortCiteRegEx": "Goldman et al\\.", "year": 1994}, {"title": "Systematic nonlinear planning", "author": ["M cAl lester", "Rosenbli tt", "1991] McAllester", "David", "Rosenblitt"], "venue": "In Proceedings of the Ninth National Con\u00ad ference on A rtificial Intelligence,", "citeRegEx": "lester et al\\.,? \\Q1991\\E", "shortCiteRegEx": "lester et al\\.", "year": 1991}, {"title": "Commitment strategies in planning: A comparative analysis", "author": ["e t al"], "venue": "In Proceedings of the 1 2th International Joint Confer\u00ad ence on A rtificial Intelligence", "citeRegEx": "al.,? \\Q1991\\E", "shortCiteRegEx": "al.", "year": 1991}, {"title": "Cassandra: Planning for contingencies", "author": ["Pryor", "Collins", "1993] Pryor", "Louise", "Gregg"], "venue": "Technical Report 41,", "citeRegEx": "Pryor et al\\.,? \\Q1993\\E", "shortCiteRegEx": "Pryor et al\\.", "year": 1993}, {"title": "Readings in Uncertain Reason\u00ad ing", "author": ["Shafer", "Pearl", "1990] Shafer", "Glenn", "Judea"], "venue": null, "citeRegEx": "Shafer et al\\.,? \\Q1990\\E", "shortCiteRegEx": "Shafer et al\\.", "year": 1990}, {"title": "Modular utility representation for decision-theoretic planning", "author": ["Wel lman", "Doyle", "1992] Wellman", "Michael P", "J Doyle"], "venue": "ed\u00ad i tor 1992, A rtificial Intelligence Planning Systems: Proceedings of the First International Conference,", "citeRegEx": "lman et al\\.,? \\Q1992\\E", "shortCiteRegEx": "lman et al\\.", "year": 1992}, {"title": "From knowl\u00ad edge bases to decision models", "author": ["Michael P. Wellman", "J ohn S . Breese", "Robert P. Goldman"], "venue": "[Well man et al.,", "citeRegEx": "Wellman et al\\.,? \\Q1992\\E", "shortCiteRegEx": "Wellman et al\\.", "year": 1992}], "referenceMentions": [{"referenceID": 7, "context": "While we agree that decision-theoretic planning is, in an ideal sense, the Right Thing, we feel that much work remains to be done before decision theoretic techniques may be combined with planners. Well\u00ad man and Doyle [1992] and more recently Haddawy and Hanks [1993] have shown that goals as used by AI plan\u00ad ners cannot be straightforwardly (i.", "startOffset": 61, "endOffset": 225}, {"referenceID": 7, "context": "While we agree that decision-theoretic planning is, in an ideal sense, the Right Thing, we feel that much work remains to be done before decision theoretic techniques may be combined with planners. Well\u00ad man and Doyle [1992] and more recently Haddawy and Hanks [1993] have shown that goals as used by AI plan\u00ad ners cannot be straightforwardly (i.", "startOffset": 61, "endOffset": 268}, {"referenceID": 7, "context": "1 K ushmerick, Hanks and Weld [1993) have indepen\u00ad dently developed an approach similar to epsilon-safe plan\u00ad ning, though the resulting plans are not conditional. Draper, et. al. [1993] are extending this framework to con\u00ad ditional plans.", "startOffset": 160, "endOffset": 187}, {"referenceID": 11, "context": "The prob\u00ad ability model employs techniques of Knowledge-based model construction [Wellman et al., 1992], which we will discuss further below.", "startOffset": 81, "endOffset": 103}, {"referenceID": 7, "context": "There exist a number of techniques for graphically rep\u00ad resenting probability and decision models (see [Pearl, 1988, Shafer and Pearl, 1990]). While these represen\u00ad tations make possible efficient inference and knowledge acquisition, they are inherently propositional and are l imited in their abilities to represent particular prob\u00ad lem instances . The KBMC approach is to encode gen\u00ad eral knowledge in an expressive language, then con\u00ad struct a decision model for each particular situation or problem instance. The interested reader can find more details on KBMC in the review by Wellman, et. al . [1992]. For the purposes of our c:-safe planner, we record knowledge about patterns of causal interaction in a knowledge-base.", "startOffset": 46, "endOffset": 607}, {"referenceID": 3, "context": "Etzioni , et. al. [1992] discuss the issues encoun\u00ad tered when planning in domains where proposi\u00ad tions may be either observed or established.", "startOffset": 0, "endOffset": 25}], "year": 2011, "abstractText": "We introduce an approach to high-level con\u00ad ditional planning we call <-safe planning. This probabilistic approach commits us to planning to meet some specified goal with a probability of success of at least I f. for some user-supplied c We describe several al\u00ad gorithms for t-safe planning based on condi\u00ad tional planners. The two conditional plan\u00ad ners we discuss are Peot and Smi th 's non\u00ad linear conditional planner, CNLP, and our own linear conditional planner, PLINTH. We present a straightforward extension to con\u00ad ditional planners for which computing the necessary probabilities is simple, employing a commonly-made but. perhaps overly-strong independence assumption. We also discuss a second approach to <-safe planning which re\u00ad laxes this independence assumption , involv\u00ad ing the incremental construction of a proba\u00ad bility dependence model in conjunction with the construction of the plan graph.", "creator": "pdftk 1.41 - www.pdftk.com"}}}